odoo10_addon_web_chatter_paste-10.0.1.0.0-py2.7-nspkg.pth
odoo10_addon_web_chatter_paste-10.0.1.0.0.dist-info/top_level.txt
odoo10_addon_web_chatter_paste-10.0.1.0.0.dist-info/WHEEL
odoo10_addon_web_chatter_paste-10.0.1.0.0.dist-info/RECORD
odoo10_addon_web_chatter_paste-10.0.1.0.0.dist-info/metadata.json
odoo10_addon_web_chatter_paste-10.0.1.0.0.dist-info/DESCRIPTION.rst
odoo10_addon_web_chatter_paste-10.0.1.0.0.dist-info/METADATA
odoo10_addon_web_chatter_paste-10.0.1.0.0.dist-info/namespace_packages.txt
odoo/addons/web_chatter_paste/__manifest__.py
odoo/addons/web_chatter_paste/__init__.py
odoo/addons/web_chatter_paste/README.rst
odoo/addons/web_chatter_paste/templates/assets.xml
odoo/addons/web_chatter_paste/controllers/main.py
odoo/addons/web_chatter_paste/controllers/__init__.py
odoo/addons/web_chatter_paste/tests/test_web_chatter_paste.py
odoo/addons/web_chatter_paste/tests/__init__.py
odoo/addons/web_chatter_paste/static/src/js/web_chatter_paste.js
